fix_utcnow/__init__.py
fix_utcnow/utcnow.py
fix_utcnow/c/libfixutcnow.so
fix_utcnow-0.5.data/data/fix_utcnow/c/libfixutcnow.so
fix_utcnow-0.5.dist-info/METADATA
fix_utcnow-0.5.dist-info/WHEEL
fix_utcnow-0.5.dist-info/top_level.txt
fix_utcnow-0.5.dist-info/RECORD
