Metadata-Version: 2.1
Name: fix-utcnow
Version: 0.5
Summary: fix-utcnow
Home-page: https://github.com/maxtwen/fix-utcnow
Author: Maksim Afanasevsky
Author-email: maxtwen1@gmail.com
License: UNKNOWN
Download-URL: https://github.com/maxtwen/fix-utcnow
Platform: UNKNOWN
